[
  {
    "name": "login",
    "path": "/login",
    "component": "D:\\\\work\\\\lenz\\\\app\\\\pages\\\\login\\\\index.vue",
    "chunkName": "pages/login/index",
    "_name": "_70edc6e6"
  },
  {
    "name": "signup",
    "path": "/signup",
    "component": "D:\\\\work\\\\lenz\\\\app\\\\pages\\\\signup\\\\index.vue",
    "chunkName": "pages/signup/index",
    "_name": "_ddaac726"
  },
  {
    "name": "table",
    "path": "/table",
    "component": "D:\\\\work\\\\lenz\\\\app\\\\pages\\\\table.vue",
    "chunkName": "pages/table",
    "_name": "_bb3f6ffe"
  },
  {
    "name": "index",
    "path": "/",
    "component": "D:\\\\work\\\\lenz\\\\app\\\\pages\\\\index.vue",
    "chunkName": "pages/index",
    "_name": "_2e75d9f6"
  }
]
